edge_tts_mcp_server/__init__.py
edge_tts_mcp_server/server.py
mseep_edge_tts_mcp_server-0.1.1.dist-info/METADATA
mseep_edge_tts_mcp_server-0.1.1.dist-info/WHEEL
mseep_edge_tts_mcp_server-0.1.1.dist-info/entry_points.txt
mseep_edge_tts_mcp_server-0.1.1.dist-info/top_level.txt
mseep_edge_tts_mcp_server-0.1.1.dist-info/RECORD
