Metadata-Version: 2.4
Name: mseep-edge_tts_mcp_server
Version: 0.1.1
Summary: MCPサーバーでedge-ttsを提供するサービス
Author-email: mseep <support@skydeck.ai>
License: MIT
Classifier: Programming Language :: Python :: 3
Classifier: License :: OSI Approved :: MIT License
Classifier: Operating System :: OS Independent
Requires-Python: >=3.10
Requires-Dist: mcp
Requires-Dist: edge-tts
Requires-Dist: uvicorn
Requires-Dist: fastapi
Provides-Extra: dev
Requires-Dist: black; extra == "dev"
Requires-Dist: isort; extra == "dev"
Requires-Dist: pytest; extra == "dev"
